xnet_system/__init__.py
xnet_system/cli.py
xnet_system/config.json
xnet_system/main.py
xnet_system/security.py
xnet_system/tools.py
xnet_toolkit-1.1.0.dist-info/METADATA
xnet_toolkit-1.1.0.dist-info/WHEEL
xnet_toolkit-1.1.0.dist-info/entry_points.txt
xnet_toolkit-1.1.0.dist-info/top_level.txt
xnet_toolkit-1.1.0.dist-info/RECORD
