Metadata-Version: 2.4
Name: xnet-toolkit
Version: 1.1.0
Summary: Professional Network Administration and Security Toolkit
Home-page: https://github.com/StasX-Official/xnet
Author: StasX (Kozosvyst Stas)
Author-email: xnet@sxservisecli.tech
Project-URL: Bug Reports, https://github.com/StasX-Official/xnet/issues
Project-URL: Source, https://github.com/StasX-Official/xnet
Keywords: network,security,administration,scanner,monitoring,tools
Classifier: Development Status :: 5 - Production/Stable
Classifier: Intended Audience :: System Administrators
Classifier: Intended Audience :: Information Technology
Classifier: Programming Language :: Python :: 3
Classifier: Programming Language :: Python :: 3.6
Classifier: Programming Language :: Python :: 3.7
Classifier: Programming Language :: Python :: 3.8
Classifier: Programming Language :: Python :: 3.9
Classifier: Programming Language :: Python :: 3.10
Classifier: License :: OSI Approved :: MIT License
Classifier: Operating System :: OS Independent
Classifier: Topic :: System :: Networking
Classifier: Topic :: System :: Systems Administration
Classifier: Topic :: Security
Requires-Python: >=3.6
Requires-Dist: asyncio>=3.4.3
Requires-Dist: ipaddress>=1.0.23
Requires-Dist: cryptography>=3.4.0
Requires-Dist: requests>=2.25.0
Requires-Dist: scapy>=2.4.0
Requires-Dist: netifaces>=0.11.0
Requires-Dist: prettytable>=2.0.0
Requires-Dist: pyOpenSSL>=20.0.0
Requires-Dist: argon2-cffi>=20.1.0
Requires-Dist: psutil>=5.8.0
Requires-Dist: dnspython>=2.1.0
Requires-Dist: graphviz>=0.16
Requires-Dist: python-iptables>=1.0.0; platform_system != "Windows"
Requires-Dist: weasyprint>=52.5
Dynamic: author
Dynamic: author-email
Dynamic: classifier
Dynamic: description
Dynamic: description-content-type
Dynamic: home-page
Dynamic: keywords
Dynamic: project-url
Dynamic: requires-dist
Dynamic: requires-python
Dynamic: summary
